argcompile/__init__.py
argcompile/main.py
argcompile/meta.py
argcompile/file/__init__.py
argcompile/file/attribute.py
argcompile/file/compiler.py
argcompile-0.0.9.dist-info/LICENSE
argcompile-0.0.9.dist-info/METADATA
argcompile-0.0.9.dist-info/WHEEL
argcompile-0.0.9.dist-info/top_level.txt
argcompile-0.0.9.dist-info/RECORD
