Metadata-Version: 2.1
Name: argcompile
Version: 0.0.9
Summary: An argparse extension to easily manage post-processing of multiple parsed arguments
Home-page: https://github.com/artu-hnrq/argcompile
Author: Arthur Henrique Della Fraga
Author-email: "Arthur Henrique Della Fraga" <Arthur.Henrique.Della.Fraga@gmail.com>
License: MIT
Platform: ANY
Classifier: Development Status :: 4 - Beta
Classifier: Intended Audience :: Developers
Classifier: Operating System :: OS Independent
Classifier: Programming Language :: Python :: 3 :: Only
Classifier: Programming Language :: Python :: 3.6
Classifier: License :: OSI Approved :: MIT License
Classifier: Topic :: Software Development :: Libraries :: Python Modules
Classifier: Topic :: Utilities
Requires-Python: >=3.6
Requires-Dist: PyYAML (==3.12)
